anki_poker_master/__init__.py
anki_poker_master/anki.py
anki_poker_master/cli.py
anki_poker_master/helper.py
anki_poker_master/resources/blank_table.html
anki_poker_master/resources/default.css
anki_poker_master/resources/default.js
anki_poker_master/resources/images/apm-card-2c.png
anki_poker_master/resources/images/apm-card-2d.png
anki_poker_master/resources/images/apm-card-2h.png
anki_poker_master/resources/images/apm-card-2s.png
anki_poker_master/resources/images/apm-card-3c.png
anki_poker_master/resources/images/apm-card-3d.png
anki_poker_master/resources/images/apm-card-3h.png
anki_poker_master/resources/images/apm-card-3s.png
anki_poker_master/resources/images/apm-card-4c.png
anki_poker_master/resources/images/apm-card-4d.png
anki_poker_master/resources/images/apm-card-4h.png
anki_poker_master/resources/images/apm-card-4s.png
anki_poker_master/resources/images/apm-card-5c.png
anki_poker_master/resources/images/apm-card-5d.png
anki_poker_master/resources/images/apm-card-5h.png
anki_poker_master/resources/images/apm-card-5s.png
anki_poker_master/resources/images/apm-card-6c.png
anki_poker_master/resources/images/apm-card-6d.png
anki_poker_master/resources/images/apm-card-6h.png
anki_poker_master/resources/images/apm-card-6s.png
anki_poker_master/resources/images/apm-card-7c.png
anki_poker_master/resources/images/apm-card-7d.png
anki_poker_master/resources/images/apm-card-7h.png
anki_poker_master/resources/images/apm-card-7s.png
anki_poker_master/resources/images/apm-card-8c.png
anki_poker_master/resources/images/apm-card-8d.png
anki_poker_master/resources/images/apm-card-8h.png
anki_poker_master/resources/images/apm-card-8s.png
anki_poker_master/resources/images/apm-card-9c.png
anki_poker_master/resources/images/apm-card-9d.png
anki_poker_master/resources/images/apm-card-9h.png
anki_poker_master/resources/images/apm-card-9s.png
anki_poker_master/resources/images/apm-card-Ac.png
anki_poker_master/resources/images/apm-card-Ad.png
anki_poker_master-0.2.0.dist-info/LICENSE
anki_poker_master-0.2.0.dist-info/METADATA
anki_poker_master-0.2.0.dist-info/WHEEL
anki_poker_master-0.2.0.dist-info/entry_points.txt
anki_poker_master-0.2.0.dist-info/RECORD
