Metadata-Version: 2.1
Name: anki_poker_master
Version: 0.2.0
Summary: 
Author: Omar Kohl
Author-email: omarkohl@posteo.net
Requires-Python: >=3.8,<4.0
Classifier: Programming Language :: Python :: 3
Classifier: Programming Language :: Python :: 3.8
Classifier: Programming Language :: Python :: 3.9
Classifier: Programming Language :: Python :: 3.10
Classifier: Programming Language :: Python :: 3.11
Classifier: Programming Language :: Python :: 3.12
Requires-Dist: genanki (>=0.13.1,<0.14.0)
Requires-Dist: importlib-resources (>=6.1.2,<7.0.0)
Requires-Dist: poker (>=0.30.0,<0.31.0)
Requires-Dist: schema (>=0.7.5,<0.8.0)
